LICENSE
README.md
setup.cfg
setup.py
panml/__init__.py
panml/constants.py
panml/environments.py
panml/models.py
panml/search.py
panml.egg-info/PKG-INFO
panml.egg-info/SOURCES.txt
panml.egg-info/dependency_links.txt
panml.egg-info/requires.txt
panml.egg-info/top_level.txt
panml/clustering/__init__.py
panml/clustering/faiss.py
panml/llm/__init__.py
panml/llm/huggingface.py
panml/llm/openai.py
test/test_ModelPack.py
test/test_VectorEngine.py