Metadata-Version: 2.1
Name: panml
Version: 1.0.3
Summary: PanML is a high level generative AI/ML development library designed for ease of use and fast experimentation.
Home-page: https://github.com/Pan-ML/panml
Author: PanML team
Author-email: teampanml@gmail.com
License: MIT
Keywords: generative AI,generative model,machine learning,large language model,LLM,prompt engineering,fine tuning,prompt tuning,retrieval augmentation,AI safety,AI alignment
Platform: UNKNOWN
Classifier: Development Status :: 4 - Beta
Classifier: Intended Audience :: Science/Research
Classifier: Intended Audience :: Developers
Classifier: Intended Audience :: Education
Classifier: Intended Audience :: Information Technology
Classifier: Topic :: Software Development :: Build Tools
Classifier: License :: OSI Approved :: MIT License
Classifier: Programming Language :: Python :: 3
Classifier: Programming Language :: Python :: 3.7
Classifier: Programming Language :: Python :: 3.8
Classifier: Programming Language :: Python :: 3.9
Classifier: Programming Language :: Python :: 3.10
Classifier: Programming Language :: Python :: 3.11
License-File: LICENSE
